headless_kivy/__init__.py
headless_kivy/_debug.py
headless_kivy/_version.py
headless_kivy/config.py
headless_kivy/constants.py
headless_kivy/logger.py
headless_kivy/utils.py
headless_kivy/widget.py
headless_kivy_pytest/__init__.py
headless_kivy_pytest/plugin.py
headless_kivy_pytest/fixtures/__init__.py
headless_kivy_pytest/fixtures/snapshot.py
headless_kivy-0.12.4.dist-info/METADATA
headless_kivy-0.12.4.dist-info/WHEEL
headless_kivy-0.12.4.dist-info/entry_points.txt
headless_kivy-0.12.4.dist-info/licenses/LICENSE
headless_kivy-0.12.4.dist-info/RECORD
