Metadata-Version: 2.4
Name: headless-kivy
Version: 0.12.4
Summary: Headless renderer for Kivy framework
Project-URL: homepage, https://github.com/sassanh/headless-kivy/
Project-URL: repository, https://github.com/sassanh/headless-kivy/
Project-URL: documentation, https://github.com/sassanh/headless-kivy/
Project-URL: changelog, https://github.com/sassanh/headless-kivy/blob/main/CHANGELOG.md
Author-email: Sassan Haradji <me@sassanh.com>
Maintainer-email: Sassan Haradji <me@sassanh.com>
License: Apache-2.0
License-File: LICENSE
Keywords: display,headless,kivy,pytest,test
Requires-Python: >=3.11
Requires-Dist: kivy>=2.2.1
Requires-Dist: numpy<2.0.0,>=1.24.2
Requires-Dist: python-strtobool>=1.0.0
Provides-Extra: test
Requires-Dist: pypng>=0.20220715.0; extra == 'test'
